emailoctopus_sdk/__init__.py
emailoctopus_sdk-0.2.0.dist-info/licenses/LICENSE
emailoctopus_sdk-0.2.0.dist-info/METADATA
emailoctopus_sdk-0.2.0.dist-info/WHEEL
emailoctopus_sdk-0.2.0.dist-info/top_level.txt
emailoctopus_sdk-0.2.0.dist-info/RECORD
