Metadata-Version: 2.4
Name: emailoctopus-sdk
Version: 0.2.0
Summary: A Python SDK for the Email Octopus V2 API.
Author-email: Luke Day <dayluke01@gmail.com>
License: MIT License
Project-URL: Homepage, https://github.com/dayluke/emailoctopus-python
Project-URL: Bug Tracker, https://github.com/dayluke/emailoctopus-python/issues
Classifier: Programming Language :: Python :: 3
Classifier: License :: OSI Approved :: MIT License
Classifier: Operating System :: OS Independent
Requires-Python: >=3.7
License-File: LICENSE
Requires-Dist: requests
Provides-Extra: dev
Requires-Dist: pytest; extra == "dev"
Requires-Dist: requests-mock; extra == "dev"
Requires-Dist: black; extra == "dev"
Dynamic: license-file
